hackhttp
