Metadata-Version: 1.0
Name: hackhttp
Version: 1.0.4
Summary: Hackhttp is an HTTP library, written in Python.
Home-page: https://github.com/BugScanTeam/hackhttp
Author: BugScanTeam
Author-email: admin@bugscan.net
License: GPL 2.0
Keywords: http
Platform: UNKNOWN
